README.rst
setup.cfg
setup.py
parpydtk2/__init__.pxd
parpydtk2/__init__.py
parpydtk2/_version.py
parpydtk2/error_handle.py
parpydtk2/imeshdb.cpp
parpydtk2/imeshdb.pxd
parpydtk2/imeshdb.pyx
parpydtk2/mapper.cpp
parpydtk2/mapper.pxd
parpydtk2/mapper.pyx
parpydtk2/mpi-compat.hpp
parpydtk2.egg-info/PKG-INFO
parpydtk2.egg-info/SOURCES.txt
parpydtk2.egg-info/dependency_links.txt
parpydtk2.egg-info/requires.txt
parpydtk2.egg-info/top_level.txt
parpydtk2/src/common.hpp
parpydtk2/src/dtk2.hpp
parpydtk2/src/field.hpp
parpydtk2/src/imeshdb.hpp