Metadata-Version: 1.1
Name: parpydtk2
Version: 1.1.1
Summary: Python Wrapper for Parallel DTK2+MOAB
Home-page: https://github.com/chiao45/parpydtk2
Author: Qiao Chen
Author-email: benechiao@gmail.com
License: MIT
Keywords: Math
Platform: UNKNOWN
Classifier: Programming Language :: Python :: 3.5
Classifier: Programming Language :: Python :: 3.6
Classifier: Programming Language :: C++
Classifier: Topic :: Scientific/Engineering
Classifier: Topic :: Software Development
Classifier: Operating System :: POSIX :: Linux
Classifier: Intended Audience :: Science/Research
Classifier: License :: OSI Approved :: MIT License
